<?xml version="1.0" encoding="ISO-8859-1"?>
<Concesionario xmlns:xsi="http://www.w3.org/2001/XMLSchema-instance" xsi:noNamespaceSchemaLocation="Concesionario.xsd">>
    
    <coche>
        <codigo-de-coche>LJCPCBLCX11000237</codigo-de-coche>
        <marca>Toyota</marca>
        <modelo>GT86</modelo>
        <matricula>1234ABC</matricula>
        <potencia>200</potencia>
        <plazas>4</plazas>
        <numero-puertas>3</numero-puertas>
    </coche>
    <coche>
        <codigo-de-coche>2ADFTV2ZRFXE1ZRFAE</codigo-de-coche>
        <marca>Toyota</marca>
        <modelo>Corolla</modelo>
        <matricula>5555GTL</matricula>
        <potencia>122</potencia>
        <plazas>7</plazas>
        <numero-puertas>5</numero-puertas>
    </coche>
    <coche>
        <codigo-de-coche>JAG8723NNAS98N129J127</codigo-de-coche>
        <marca>Seat</marca>
        <modelo>Leon</modelo>
        <matricula>0745GAT</matricula>
        <potencia>130</potencia>
        <plazas>4</plazas>
        <numero-puertas>5</numero-puertas>
    </coche>
    <coche>
        <codigo-de-coche>1PFM98AQNB09M2097</codigo-de-coche>
        <marca>Volkswagen</marca> 
        <modelo>Golf</modelo>
        <matricula>5719BOT</matricula>
        <potencia>110</potencia>
        <plazas>4</plazas>
        <numero-puertas>5</numero-puertas>
    </coche>
    <coche>
        <codigo-de-coche>M187BS6VNC09A6123</codigo-de-coche>
        <marca>Mitsubishi</marca> 
        <modelo>Montero</modelo>
        <matricula>1290GXT</matricula>
        <potencia>200</potencia>
        <plazas>7</plazas>
        <numero-puertas>5</numero-puertas>
    </coche>
    <coche>
        <codigo-de-coche>AHMJ199844AS51H984</codigo-de-coche>
        <marca>Citroen</marca>
        <modelo>Berlingo</modelo>
        <matricula>1029HBW</matricula>
        <potencia>136</potencia>
        <plazas>5</plazas>
        <numero-puertas>5</numero-puertas>
    </coche>
        <coche>
        <codigo-de-coche>M18BS875A980921B3</codigo-de-coche>
        <marca>Fiat</marca>
        <modelo>500</modelo>
        <matricula>4875POI</matricula>
        <potencia>118</potencia>
        <plazas>4</plazas>
        <numero-puertas>3</numero-puertas>
    </coche>
        <coche>
        <codigo-de-coche>H612093NJS09U123N0</codigo-de-coche>
        <marca>Honda</marca>
        <modelo>Civic</modelo>
        <matricula>1993BBG</matricula>
        <potencia>184</potencia>
        <plazas>5</plazas>
        <numero-puertas>5</numero-puertas>
    </coche>
        <coche>
        <codigo-de-coche>L88BS67BS098B12873B</codigo-de-coche>
        <marca>Peugeot</marca>
        <modelo>2008</modelo>
        <matricula>5556GGA</matricula>
        <potencia>130</potencia>
        <plazas>5</plazas>
        <numero-puertas>5</numero-puertas>
    </coche>
        <coche>
        <codigo-de-coche>T623J8UASM0912983N</codigo-de-coche>
        <marca>Renault</marca>
        <modelo>Megane</modelo>
        <matricula>8751QWL</matricula>
        <potencia>115</potencia>
        <plazas>5</plazas>
        <numero-puertas>5</numero-puertas>
    </coche>
</Concesionario>